Workbook

Sheet 📋 Tracker
E1: 7TH – 14TH SEPTEMBER | G1: 15TH – 22TH SEPTEMBER | I1: 25TH SEPT- 1ST OCTOBER | K1: 2ND- 6TH OCTOBER | M1: 7TH- 11TH OCTOBER | O1: 12TH- 25TH OCTOBER
B2: CFA LEVEL 1 – 2027 CURRICULUM TRACKER (102 Learning Modules) | E2: Revision | F2: Questions | G2: Revision | H2: Questions | I2: Revision | J2: Questions | K2: Revision | L2: Questions | M2: Revision | N2: Questions | O2: Revision | P2: Questions
B3: Type 1 in the Status column to mark a module done → it turns ✅ automatically
B4: LM # | C4: Reading Name | D4: Status | E4: Status | F4: Status | G4: Status | H4: Status | I4: Status | J4: Status | K4: Status | L4: Status | M4: Status | N4: Status | O4: Status | P4: Status
B5: QUANTITATIVE METHODS
B6: 1 | C6: Returns of Financial Assets and Instruments | D6: 1 | E6: 1
B7: 2 | C7: Types of Financial Returns | D7: 1 | E7: 1
B8: 3 | C8: Benchmarking Returns | D8: 1 | E8: 1
B9: 4 | C9: The Time Value of Money in Finance | D9: 1 | E9: 1
B10: 5 | C10: Statistical Characteristics of Asset Returns | D10: 1 | E10: 1
B11: 6 | C11: Statistical Distributions for Financial Asset Prices and Returns | D11: 1 | E11: 1
B12: 7 | C12: Estimation and Hypothesis Testing | D12: 1 | E12: 1
B13: 8 | C13: The Return and Risk of a Financial Portfolio | D13: 1 | E13: 1
B14: 9 | C14: Simulation of Financial Asset Prices and Returns | D14: 1 | E14: 1
B15: 10 | C15: Applications of Simple Linear Regression in Finance | D15: 1 | E15: 1
B16: 11 | C16: Introduction to Financial Data Science | D16: 1 | E16: 1
B17: ECONOMICS
B18: 12 | C18: The Firm & Market Structures | D18: 1 | G18: 1
B19: 13 | C19: Understanding Business Cycles | D19: 1 | G19: 1
B20: 14 | C20: Fiscal Policy | D20: 1 | G20: 1
B21: 15 | C21: Monetary Policy | D21: 1 | G21: 1
B22: 16 | C22: Introduction to Geopolitics | D22: 1 | G22: 1
B23: 17 | C23: International Trade | D23: 1 | G23: 1
B24: 18 | C24: Capital Flows and the FX Market | D24: 1 | G24: 1
B25: 19 | C25: Exchange Rate Calculations | D25: 1 | G25: 1
B26: CORPORATE FINANCE
B27: 20 | C27: Organizational Forms, Corporate Issuer Features, and Ownership | D27: 1 | E27: 1
B28: 21 | C28: Investors and Other Stakeholders | D28: 1 | E28: 1
B29: 22 | C29: Corporate Governance: Conflicts, Mechanisms, Risks, and Benefits | D29: 1 | E29: 1
B30: 23 | C30: Working Capital and Liquidity | D30: 1 | E30: 1
B31: 24 | C31: Capital Investments and Capital Allocation | D31: 1 | E31: 1
B32: 25 | C32: Capital Structure | D32: 1 | E32: 1
B33: 26 | C33: Business Models | D33: 1 | E33: 1
B34: FINANCIAL STATEMENT ANALYSIS
B35: 27 | C35: Introduction to Financial Statement Analysis | D35: 1 | I35: 1 | K35: 2
B36: 28 | C36: Analyzing Income Statements | D36: 1 | I36: 1 | K36: 2
B37: 29 | C37: Analyzing Balance Sheets | D37: 1 | I37: 2 | K37: 2
B38: 30 | C38: Analyzing Statements of Cash Flows I | D38: 1 | I38: 2 | K38: 2
B39: 31 | C39: Analyzing Statements of Cash Flows II | D39: 1 | I39: 2 | K39: 2
B40: 32 | C40: Analysis of Inventories | D40: 1 | I40: 2 | K40: 2
B41: 33 | C41: Analysis of Long-Term Assets | D41: 1 | I41: 2 | K41: 2
B42: 34 | C42: Topics in Long-Term Liabilities and Equity | D42: 1 | I42: 2 | K42: 2
B43: 35 | C43: Analysis of Income Taxes | D43: 1 | I43: 2 | K43: 2
B44: 36 | C44: Financial Reporting Quality | D44: 1 | I44: 2 | K44: 2
B45: 37 | C45: Financial Analysis Techniques | D45: 1 | I45: 2 | K45: 2
B46: 38 | C46: Introduction to Financial Statement Modelling | D46: 1 | I46: 2 | K46: 2
B47: EQUITIES
B48: 39 | C48: Equity Instrument Features | D48: 1 | O48: 2
B49: 40 | C49: Equity Jurisdictions, Classes, and the Voting Process | D49: 1 | O49: 2
B50: 41 | C50: Equity Issuance and Trading | D50: 1 | O50: 2
B51: 42 | C51: Sources of Equity Returns | D51: 1 | O51: 2
B52: 43 | C52: Introduction to Equity Valuation | D52: 1 | O52: 2
B53: 44 | C53: Discounted Cash Flow and Growth Models | D53: 1 | O53: 2
B54: 45 | C54: Relative Value Equity Valuation Approaches | D54: 1 | O54: 2
B55: 46 | C55: Financial Statement Forecasting in Equity Valuation | D55: 1 | O55: 2
B56: 47 | C56: Industry and Competitive Analysis | D56: 1 | O56: 2
B57: 48 | C57: Company Analysis: Past, Present, and Future | D57: 1 | O57: 2
B58: 49 | C58: Equity Analyst Research Reports | D58: 1 | O58: 2
B59: 50 | C59: The Capital Asset Pricing Model, Market Model, and Other Factor-Based Equity Models | D59: 1 | O59: 2
B60: FIXED INCOME
B61: 51 | C61: Fixed-Income Instrument Features | D61: 1 | O61: 2
B62: 52 | C62: Fixed-Income Cash Flows and Types | D62: 1 | O62: 2
B63: 53 | C63: Fixed-Income Issuance and Trading | D63: 1 | O63: 2
B64: 54 | C64: Fixed-Income Markets for Corporate Issuers | D64: 1 | O64: 2
B65: 55 | C65: Fixed-Income Markets for Government Issuers | D65: 1 | O65: 2
B66: 56 | C66: Fixed-Income Bond Valuation: Prices and Yields | D66: 1 | O66: 2
B67: 57 | C67: Yield and Yield Spread Measures for Fixed-Rate Bonds | D67: 1 | O67: 2
B68: 58 | C68: Yield and Yield Spread Measures for Floating-Rate Instruments | D68: 1 | O68: 2
B69: 59 | C69: The Term Structure of Interest Rates: Spot, Par, and Forward Curves | D69: 1 | O69: 2
B70: 60 | C70: Interest Rate Risk and Return | D70: 1 | O70: 2
B71: 61 | C71: Yield-Based Bond Duration Measures and Properties | D71: 1 | O71: 2
B72: 62 | C72: Yield-Based Bond Convexity and Portfolio Properties | D72: 1 | O72: 2
... B79: 69 | C79: Mortgage-Backed Security (MBS) Instrument and Market Features | D79: 1 | O79: 2
B80: DERIVATIVES
B81: 70 | C81: Derivative Instrument and Derivative Market Features | D81: 1 | K81: 2 | M81: 2
B82: 71 | C82: Forward Commitment and Contingent Claim Features and Instruments | D82: 1 | K82: 2 | M82: 2
B83: 72 | C83: Derivative Benefits, Risks, and Issuer and Investor Uses | D83: 1 | K83: 2 | M83: 2
B84: 73 | C84: Arbitrage, Replication, and the Cost of Carry in Pricing Derivatives | D84: 1 | K84: 2 | M84: 2
B85: 74 | C85: Pricing and Valuation of Forward Contracts | D85: 1 | K85: 2 | M85: 2
B86: 75 | C86: Pricing and Valuation of Futures Contracts | D86: 1 | K86: 2 | M86: 2
B87: 76 | C87: Pricing and Valuation of Interest Rate and Other Swaps | D87: 1 | K87: 2 | M87: 2
B88: 77 | C88: Pricing and Valuation of Options | D88: 1 | K88: 2 | M88: 2
B89: 78 | C89: Option Replication Using Put-Call Parity | D89: 1 | K89: 2 | M89: 2
B90: 79 | C90: Valuing a Derivative Using a One-Period Binomial Model | D90: 1 | K90: 2 | M90: 2
B91: ALTERNATIVE INVESTMENTS
B92: 80 | C92: Alternative Investment Features, Methods, and Structures | D92: 1 | I92: 1
B93: 81 | C93: Alternative Investment Performance and Returns | D93: 1 | I93: 2
B94: 82 | C94: Investments in Private Capital: Equity and Debt | D94: 1 | I94: 2
B95: 83 | C95: Real Estate and Infrastructure | D95: 1 | I95: 2
B96: 84 | C96: Natural Resources | D96: 1 | I96: 2
B97: 85 | C97: Hedge Funds | D97: 1 | I97: 2
B98: 86 | C98: Introduction to Digital Assets | D98: 1 | I98: 2
B99: Portfolio Construction
B100: 87 | C100: Portfolio Risk & Return: Part I | D100: 1 | G100: 1
B101: 88 | C101: Portfolio Risk & Return: Part II | D101: 1 | G101: 1
B102: 89 | C102: Portfolio Construction: An Overview | D102: 1 | G102: 1
B103: 90 | C103: Basics of Portfolio Planning & Construction | D103: 1 | G103: 1
B104: 91 | C104: The Behavioural Biases of Individuals | D104: 1 | G104: 1
B105: 92 | C105: Introduction to Risk Management | D105: 1 | G105: 1
B106: ETHICS
...

Sheet 📊 Dashboard
B1: CFA LEVEL 1 – PROGRESS BY TOPIC (2027)
B2: Go to the Tracker sheet → type 1 to mark done → this dashboard updates automatically
B3: Topic | C3: Total LMs | D3: Completed | E3: Progress
B4: Quantitative Methods | C4: 11 | D4: =COUNTIF('📋 Tracker'!D6:D16,1) -> 11 | E4: =D4/C4 -> 1
B5: Economics | C5: 8 | D5: =COUNTIF('📋 Tracker'!D18:D25,1) -> 8 | E5: =D5/C5 -> 1
B6: Corporate Finance | C6: 7 | D6: =COUNTIF('📋 Tracker'!D27:D33,1) -> 7 | E6: =D6/C6 -> 1
B7: Financial Statement Analysis | C7: 12 | D7: =COUNTIF('📋 Tracker'!D35:D46,1) -> 12 | E7: =D7/C7 -> 1
B8: Equities | C8: 12 | D8: =COUNTIF('📋 Tracker'!D48:D59,1) -> 12 | E8: =D8/C8 -> 1
B9: Fixed Income | C9: 19 | D9: =COUNTIF('📋 Tracker'!D61:D79,1) -> 19 | E9: =D9/C9 -> 1
B10: Derivatives | C10: 10 | D10: =COUNTIF('📋 Tracker'!D81:D90,1) -> 10 | E10: =D10/C10 -> 1
B11: Alternative Investments | C11: 7 | D11: =COUNTIF('📋 Tracker'!D92:D98,1) -> 7 | E11: =D11/C11 -> 1
B12: Portfolio Construction | C12: 6 | D12: =COUNTIF('📋 Tracker'!D100:D105,1) -> 6 | E12: =D12/C12 -> 1
B13: Ethics | C13: 10 | D13: =COUNTIF('📋 Tracker'!D107:D116,1) -> 10 | E13: =D13/C13 -> 1
B14: TOTAL | C14: 102 | D14: =SUM(D4:D13) -> 102 | E14: =D14/102 -> 1
B16: ="Overall: "&TEXT(D14/102,"0.0%")&" complete ("&D14&" / 102 LMs)" -> Overall: 100.0% complete (102 / 102 LMs)
B18: EXAM TOPIC WEIGHTS (CFA Level 1 – 2027)
B19: Topic | C19: Exam Weight | D19: Min % | E19: Max %
B20: Ethics | C20: 15–20% | D20: 0.15 | E20: 0.2
B21: Equities | C21: 11–14% | D21: 0.11 | E21: 0.14
B22: Financial Statement Analysis | C22: 11–14% | D22: 0.11 | E22: 0.14
B23: Fixed Income | C23: 11–14% | D23: 0.11 | E23: 0.14
B24: Quantitative Methods | C24: 11–14% | D24: 0.11 | E24: 0.14
B25: Portfolio Construction | C25: 8–12% | D25: 0.08 | E25: 0.12
B26: Alternative Investments | C26: 6–9% | D26: 0.06 | E26: 0.09
B27: Corporate Finance | C27: 6–9% | D27: 0.06 | E27: 0.09
B28: Economics | C28: 6–9% | D28: 0.06 | E28: 0.09
B29: Derivatives | C29: 6–9% | D29: 0.06 | E29: 0.09
B30: Source: CFA Institute 2027 Level I Exam Topic Area Weights
